datamultiproc/__init__.py
datamultiproc/composer.py
datamultiproc/fileio.py
datamultiproc/processor.py
datamultiproc/sample.py
datamultiproc/test_fileio.py
datamultiproc/test_sample.py
datamultiproc/utils.py
datamultiproc-0.1.3.dist-info/LICENSE
datamultiproc-0.1.3.dist-info/WHEEL
datamultiproc-0.1.3.dist-info/METADATA
datamultiproc-0.1.3.dist-info/RECORD
