Metadata-Version: 2.1
Name: datamultiproc
Version: 0.1.3
Summary: A Python multiprocessing library for data processing with pipelines.
Home-page: https://github.com/mglasder/datamultiproc
License: MIT
Author: Magnus Glasder
Requires-Python: >=3.9,<4.0
Classifier: License :: OSI Approved :: MIT License
Classifier: Programming Language :: Python :: 3
Classifier: Programming Language :: Python :: 3.10
Classifier: Programming Language :: Python :: 3.9
Requires-Dist: PyYAML (>=6.0,<7.0)
Requires-Dist: assertpy (>=1.1,<2.0)
Requires-Dist: numpy (>=1.24.3,<2.0.0)
Requires-Dist: pydantic (>=1.10.7,<2.0.0)
Requires-Dist: pydantic-yaml (>=0.11.2,<0.12.0)
Requires-Dist: pytest (>=7.3.1,<8.0.0)
